<?xml version="1.0" encoding="UTF-8"?>
<sbml xmlns="http://www.sbml.org/sbml/level2/version4" level="2" version="4">
  <model id="MPModel">
    <notes>
      <body xmlns="http://www.w3.org/1999/xhtml">
        <p>
          <h2>
            <center>Perceptron</center>
          </h2>
        </p>
        <p>Description: Perceptron</p>
        <p>This model has been automatically generated by the MetaPlab SBML plugin.<br/>
The original model has <b>time unit = 0.1 seconds</b> and <b>time resolution = 1.0</b>
        <br/>
In order to obtain the same dynamics of the original model, the user should calculate it by means of the <b>Euler algorithm with dT = 1.0</b> (which corresponds to 0.1 seconds)</p>
      </body>
    </notes>
    <listOfCompartments>
      <compartment id="skin" name="skin membrane" size="1" units="volume"/>
    </listOfCompartments>
    <listOfSpecies>
      <species id="X1v0" name="Substance" compartment="skin" initialConcentration="1" substanceUnits="substance" boundaryCondition="true" constant="true"/>
      <species id="X2v0" name="Substance" compartment="skin" initialConcentration="1" substanceUnits="substance" boundaryCondition="true" constant="true"/>
      <species id="W2po" name="Substance" compartment="skin" initialConcentration="9" substanceUnits="substance" boundaryCondition="true" constant="true"/>
      <species id="W0ne" name="Substance" compartment="skin" initialConcentration="5" substanceUnits="substance" boundaryCondition="true" constant="true"/>
      <species id="W1po" name="Substance" compartment="skin" initialConcentration="8" substanceUnits="substance" boundaryCondition="true" constant="true"/>
      <species id="X1v1" name="Substance" compartment="skin" initialConcentration="0" substanceUnits="substance" boundaryCondition="true" constant="true"/>
      <species id="X2v1" name="Substance" compartment="skin" initialConcentration="0" substanceUnits="substance" boundaryCondition="true" constant="true"/>
      <species id="Zpo" name="Substance" compartment="skin" initialConcentration="0" substanceUnits="substance" boundaryCondition="true" constant="true"/>
      <species id="W1pox" name="Substance" compartment="skin" initialConcentration="0" substanceUnits="substance" boundaryCondition="true" constant="true"/>
      <species id="W2pox" name="Substance" compartment="skin" initialConcentration="0" substanceUnits="substance" boundaryCondition="true" constant="true"/>
      <species id="W0nex" name="Substance" compartment="skin" initialConcentration="0" substanceUnits="substance" boundaryCondition="true" constant="true"/>
      <species id="Zne" name="Substance" compartment="skin" initialConcentration="0" substanceUnits="substance" boundaryCondition="true" constant="true"/>
      <species id="Yv0" name="Substance" compartment="skin" initialConcentration="0" substanceUnits="substance" boundaryCondition="true" constant="true"/>
      <species id="Yv1" name="Substance" compartment="skin" initialConcentration="0" substanceUnits="substance" boundaryCondition="true" constant="true"/>
      <species id="Dv1" name="Substance" compartment="skin" initialConcentration="0" substanceUnits="substance" boundaryCondition="true" constant="true"/>
      <species id="Dv0" name="Substance" compartment="skin" initialConcentration="1" substanceUnits="substance" boundaryCondition="true" constant="true"/>
      <species id="W1ne" name="Substance" compartment="skin" initialConcentration="0" substanceUnits="substance" boundaryCondition="true" constant="true"/>
      <species id="W1nex" name="Substance" compartment="skin" initialConcentration="0" substanceUnits="substance" boundaryCondition="true" constant="true"/>
      <species id="W2ne" name="Substance" compartment="skin" initialConcentration="0" substanceUnits="substance" boundaryCondition="true" constant="true"/>
      <species id="W2nex" name="Substance" compartment="skin" initialConcentration="0" substanceUnits="substance" boundaryCondition="true" constant="true"/>
      <species id="W0pox" name="Substance" compartment="skin" initialConcentration="0" substanceUnits="substance" boundaryCondition="true" constant="true"/>
      <species id="W0po" name="Substance" compartment="skin" initialConcentration="0" substanceUnits="substance" boundaryCondition="true" constant="true"/>
    </listOfSpecies>
    <listOfParameters>
      <parameter id="I" name="Inertia" value="100" units="dimensionless">
        <notes>
          <body xmlns="http://www.w3.org/1999/xhtml">
            <p>MP measure unit: mol</p>
          </body>
        </notes>
      </parameter>
      <parameter id="WxSum" name="Parameter" value="0" units="dimensionless" constant="false"/>
      <parameter id="WSum" name="Parameter" value="0" units="dimensionless" constant="false"/>
      <parameter id="WSumNegF" name="Parameter" value="0" units="dimensionless" constant="false"/>
      <parameter id="XSum" name="Parameter" value="2" units="dimensionless" constant="false"/>
      <parameter id="XSumNegF" name="Parameter" value="0" units="dimensionless" constant="false"/>
    </listOfParameters>
    <listOfRules>
      <assignmentRule metaid="WxSumEvolution" variable="WxSum">
        <math xmlns="http://www.w3.org/1998/Math/MathML">
          <apply>
            <plus/>
            <ci> W0pox </ci>
            <ci> W0nex </ci>
            <ci> W1pox </ci>
            <ci> W1nex </ci>
            <ci> W2pox </ci>
            <ci> W2nex </ci>
          </apply>
        </math>
      </assignmentRule>
      <assignmentRule metaid="WSumEvolution" variable="WSum">
        <math xmlns="http://www.w3.org/1998/Math/MathML">
          <apply>
            <plus/>
            <ci> W0po </ci>
            <ci> W0ne </ci>
            <ci> W1po </ci>
            <ci> W1ne </ci>
            <ci> W2po </ci>
            <ci> W2ne </ci>
          </apply>
        </math>
      </assignmentRule>
      <assignmentRule metaid="WSumNegFEvolution" variable="WSumNegF">
        <math xmlns="http://www.w3.org/1998/Math/MathML">
          <apply>
            <divide/>
            <cn> 0.08 </cn>
            <apply>
              <power/>
              <apply>
                <plus/>
                <cn> 3.3 </cn>
                <apply>
                  <times/>
                  <cn> 0.2 </cn>
                  <ci> WSum </ci>
                </apply>
              </apply>
              <cn> 2 </cn>
            </apply>
          </apply>
        </math>
      </assignmentRule>
      <assignmentRule metaid="XSumEvolution" variable="XSum">
        <math xmlns="http://www.w3.org/1998/Math/MathML">
          <apply>
            <plus/>
            <ci> X1v0 </ci>
            <ci> X1v1 </ci>
            <ci> X2v0 </ci>
            <ci> X2v1 </ci>
          </apply>
        </math>
      </assignmentRule>
      <assignmentRule metaid="XSumNegFEvolution" variable="XSumNegF">
        <math xmlns="http://www.w3.org/1998/Math/MathML">
          <apply>
            <divide/>
            <cn> 2 </cn>
            <apply>
              <plus/>
              <cn> 1 </cn>
              <apply>
                <times/>
                <cn> 4 </cn>
                <ci> XSum </ci>
              </apply>
            </apply>
          </apply>
        </math>
      </assignmentRule>
    </listOfRules>
    <listOfReactions>
      <reaction id="R4" reversible="false" fast="false">
        <listOfReactants>
          <speciesReference species="W1po"/>
        </listOfReactants>
        <listOfProducts>
          <speciesReference species="W1pox"/>
        </listOfProducts>
        <listOfModifiers>
          <modifierSpeciesReference species="X1v0"/>
        </listOfModifiers>
        <kineticLaw>
          <notes>
            <body xmlns="http://www.w3.org/1999/xhtml">
              <p>Flux name: F4</p>
            </body>
          </notes>
          <math xmlns="http://www.w3.org/1998/Math/MathML">
            <apply>
              <times/>
              <cn> 0.1 </cn>
              <apply>
                <power/>
                <ci> X1v0 </ci>
                <cn> 2 </cn>
              </apply>
              <ci> W1po </ci>
            </apply>
          </math>
        </kineticLaw>
      </reaction>
      <reaction id="R10" reversible="false" fast="false">
        <listOfReactants>
          <speciesReference species="W2po"/>
        </listOfReactants>
        <listOfProducts>
          <speciesReference species="Zpo"/>
          <speciesReference species="W2pox"/>
        </listOfProducts>
        <listOfModifiers>
          <modifierSpeciesReference species="X2v1"/>
        </listOfModifiers>
        <kineticLaw>
          <notes>
            <body xmlns="http://www.w3.org/1999/xhtml">
              <p>Flux name: F10</p>
            </body>
          </notes>
          <math xmlns="http://www.w3.org/1998/Math/MathML">
            <apply>
              <times/>
              <cn> 0.1 </cn>
              <apply>
                <power/>
                <ci> X2v1 </ci>
                <cn> 2 </cn>
              </apply>
              <ci> W2po </ci>
            </apply>
          </math>
        </kineticLaw>
      </reaction>
      <reaction id="R9" reversible="false" fast="false">
        <listOfReactants>
          <speciesReference species="W2po"/>
        </listOfReactants>
        <listOfProducts>
          <speciesReference species="W2pox"/>
        </listOfProducts>
        <listOfModifiers>
          <modifierSpeciesReference species="X2v0"/>
        </listOfModifiers>
        <kineticLaw>
          <notes>
            <body xmlns="http://www.w3.org/1999/xhtml">
              <p>Flux name: F9</p>
            </body>
          </notes>
          <math xmlns="http://www.w3.org/1998/Math/MathML">
            <apply>
              <times/>
              <cn> 0.1 </cn>
              <apply>
                <power/>
                <ci> X2v0 </ci>
                <cn> 2 </cn>
              </apply>
              <ci> W2po </ci>
            </apply>
          </math>
        </kineticLaw>
      </reaction>
      <reaction id="R5" reversible="false" fast="false">
        <listOfReactants>
          <speciesReference species="W1po"/>
        </listOfReactants>
        <listOfProducts>
          <speciesReference species="Zpo"/>
          <speciesReference species="W1pox"/>
        </listOfProducts>
        <listOfModifiers>
          <modifierSpeciesReference species="X1v1"/>
        </listOfModifiers>
        <kineticLaw>
          <notes>
            <body xmlns="http://www.w3.org/1999/xhtml">
              <p>Flux name: F5</p>
            </body>
          </notes>
          <math xmlns="http://www.w3.org/1998/Math/MathML">
            <apply>
              <times/>
              <cn> 0.1 </cn>
              <apply>
                <power/>
                <ci> X1v1 </ci>
                <cn> 2 </cn>
              </apply>
              <ci> W1po </ci>
            </apply>
          </math>
        </kineticLaw>
      </reaction>
      <reaction id="R2" reversible="false" fast="false">
        <listOfReactants>
          <speciesReference species="W0ne"/>
        </listOfReactants>
        <listOfProducts>
          <speciesReference species="W0nex"/>
          <speciesReference species="Zne"/>
        </listOfProducts>
        <kineticLaw>
          <notes>
            <body xmlns="http://www.w3.org/1999/xhtml">
              <p>Flux name: F2</p>
            </body>
          </notes>
          <math xmlns="http://www.w3.org/1998/Math/MathML">
            <apply>
              <times/>
              <cn> 0.025 </cn>
              <ci> W0ne </ci>
              <apply>
                <power/>
                <ci> XSum </ci>
                <cn> 2 </cn>
              </apply>
            </apply>
          </math>
        </kineticLaw>
      </reaction>
      <reaction id="R14" reversible="false" fast="false">
        <listOfReactants>
          <speciesReference species="Zpo"/>
          <speciesReference species="Zne"/>
        </listOfReactants>
        <kineticLaw>
          <notes>
            <body xmlns="http://www.w3.org/1999/xhtml">
              <p>Flux name: F14</p>
            </body>
          </notes>
          <math xmlns="http://www.w3.org/1998/Math/MathML">
            <piecewise>
              <piece>
                <apply>
                  <times/>
                  <cn> 0.5 </cn>
                  <ci> Zne </ci>
                </apply>
                <apply>
                  <lt/>
                  <ci> Zne </ci>
                  <ci> Zpo </ci>
                </apply>
              </piece>
              <otherwise>
                <apply>
                  <times/>
                  <cn> 0.5 </cn>
                  <ci> Zpo </ci>
                </apply>
              </otherwise>
            </piecewise>
          </math>
        </kineticLaw>
      </reaction>
      <reaction id="R15" reversible="false" fast="false">
        <listOfReactants>
          <speciesReference species="Zpo"/>
        </listOfReactants>
        <listOfProducts>
          <speciesReference species="Yv1"/>
        </listOfProducts>
        <listOfModifiers>
          <modifierSpeciesReference species="Zne"/>
        </listOfModifiers>
        <kineticLaw>
          <notes>
            <body xmlns="http://www.w3.org/1999/xhtml">
              <p>Flux name: F15</p>
            </body>
          </notes>
          <math xmlns="http://www.w3.org/1998/Math/MathML">
            <apply>
              <divide/>
              <apply>
                <times/>
                <cn> 0.01 </cn>
                <ci> Zpo </ci>
              </apply>
              <apply>
                <plus/>
                <cn> 1 </cn>
                <ci> Zne </ci>
              </apply>
            </apply>
          </math>
        </kineticLaw>
      </reaction>
      <reaction id="R16" reversible="false" fast="false">
        <listOfReactants>
          <speciesReference species="Zne"/>
        </listOfReactants>
        <listOfProducts>
          <speciesReference species="Yv0"/>
        </listOfProducts>
        <listOfModifiers>
          <modifierSpeciesReference species="Zpo"/>
        </listOfModifiers>
        <kineticLaw>
          <notes>
            <body xmlns="http://www.w3.org/1999/xhtml">
              <p>Flux name: F16</p>
            </body>
          </notes>
          <math xmlns="http://www.w3.org/1998/Math/MathML">
            <apply>
              <divide/>
              <apply>
                <times/>
                <cn> 0.01 </cn>
                <ci> Zne </ci>
              </apply>
              <apply>
                <plus/>
                <cn> 1 </cn>
                <ci> Zpo </ci>
              </apply>
            </apply>
          </math>
        </kineticLaw>
      </reaction>
      <reaction id="R30" reversible="false" fast="false">
        <listOfReactants>
          <speciesReference species="Dv0"/>
        </listOfReactants>
        <kineticLaw>
          <notes>
            <body xmlns="http://www.w3.org/1999/xhtml">
              <p>Flux name: F30</p>
            </body>
          </notes>
          <math xmlns="http://www.w3.org/1998/Math/MathML">
            <apply>
              <times/>
              <cn> 0.001 </cn>
              <ci> Dv0 </ci>
              <ci> XSumNegF </ci>
            </apply>
          </math>
        </kineticLaw>
      </reaction>
      <reaction id="R37" reversible="false" fast="false">
        <listOfReactants>
          <speciesReference species="Dv1"/>
        </listOfReactants>
        <listOfProducts>
          <speciesReference species="W2po"/>
        </listOfProducts>
        <listOfModifiers>
          <modifierSpeciesReference species="Yv0"/>
          <modifierSpeciesReference species="X2v1"/>
        </listOfModifiers>
        <kineticLaw>
          <notes>
            <body xmlns="http://www.w3.org/1999/xhtml">
              <p>Flux name: F37</p>
            </body>
          </notes>
          <math xmlns="http://www.w3.org/1998/Math/MathML">
            <apply>
              <times/>
              <cn> 0.006 </cn>
              <ci> Dv1 </ci>
              <ci> Yv0 </ci>
              <ci> X2v1 </ci>
            </apply>
          </math>
        </kineticLaw>
      </reaction>
      <reaction id="R34" reversible="false" fast="false">
        <listOfReactants>
          <speciesReference species="Dv0"/>
        </listOfReactants>
        <listOfProducts>
          <speciesReference species="W2ne"/>
        </listOfProducts>
        <listOfModifiers>
          <modifierSpeciesReference species="Yv1"/>
          <modifierSpeciesReference species="X2v1"/>
        </listOfModifiers>
        <kineticLaw>
          <notes>
            <body xmlns="http://www.w3.org/1999/xhtml">
              <p>Flux name: F34</p>
            </body>
          </notes>
          <math xmlns="http://www.w3.org/1998/Math/MathML">
            <apply>
              <times/>
              <cn> 0.006 </cn>
              <ci> Dv0 </ci>
              <ci> Yv1 </ci>
              <ci> X2v1 </ci>
            </apply>
          </math>
        </kineticLaw>
      </reaction>
      <reaction id="R31" reversible="false" fast="false">
        <listOfReactants>
          <speciesReference species="Dv1"/>
        </listOfReactants>
        <kineticLaw>
          <notes>
            <body xmlns="http://www.w3.org/1999/xhtml">
              <p>Flux name: F31</p>
            </body>
          </notes>
          <math xmlns="http://www.w3.org/1998/Math/MathML">
            <apply>
              <times/>
              <cn> 0.001 </cn>
              <ci> Dv1 </ci>
              <ci> XSumNegF </ci>
            </apply>
          </math>
        </kineticLaw>
      </reaction>
      <reaction id="R17" reversible="false" fast="false">
        <listOfReactants>
          <speciesReference species="X1v0"/>
        </listOfReactants>
        <kineticLaw>
          <notes>
            <body xmlns="http://www.w3.org/1999/xhtml">
              <p>Flux name: F17</p>
            </body>
          </notes>
          <math xmlns="http://www.w3.org/1998/Math/MathML">
            <apply>
              <times/>
              <ci> X1v0 </ci>
              <ci> WSumNegF </ci>
            </apply>
          </math>
        </kineticLaw>
      </reaction>
      <reaction id="R18" reversible="false" fast="false">
        <listOfReactants>
          <speciesReference species="X1v1"/>
        </listOfReactants>
        <kineticLaw>
          <notes>
            <body xmlns="http://www.w3.org/1999/xhtml">
              <p>Flux name: F18</p>
            </body>
          </notes>
          <math xmlns="http://www.w3.org/1998/Math/MathML">
            <apply>
              <times/>
              <ci> X1v1 </ci>
              <ci> WSumNegF </ci>
            </apply>
          </math>
        </kineticLaw>
      </reaction>
      <reaction id="R20" reversible="false" fast="false">
        <listOfReactants>
          <speciesReference species="X2v1"/>
        </listOfReactants>
        <kineticLaw>
          <notes>
            <body xmlns="http://www.w3.org/1999/xhtml">
              <p>Flux name: F20</p>
            </body>
          </notes>
          <math xmlns="http://www.w3.org/1998/Math/MathML">
            <apply>
              <times/>
              <ci> X2v1 </ci>
              <ci> WSumNegF </ci>
            </apply>
          </math>
        </kineticLaw>
      </reaction>
      <reaction id="R19" reversible="false" fast="false">
        <listOfReactants>
          <speciesReference species="X2v0"/>
        </listOfReactants>
        <kineticLaw>
          <notes>
            <body xmlns="http://www.w3.org/1999/xhtml">
              <p>Flux name: F19</p>
            </body>
          </notes>
          <math xmlns="http://www.w3.org/1998/Math/MathML">
            <apply>
              <times/>
              <ci> X2v0 </ci>
              <ci> WSumNegF </ci>
            </apply>
          </math>
        </kineticLaw>
      </reaction>
      <reaction id="R23" reversible="false" fast="false">
        <listOfReactants>
          <speciesReference species="W1pox"/>
        </listOfReactants>
        <listOfProducts>
          <speciesReference species="W1po"/>
        </listOfProducts>
        <kineticLaw>
          <notes>
            <body xmlns="http://www.w3.org/1999/xhtml">
              <p>Flux name: F23</p>
            </body>
          </notes>
          <math xmlns="http://www.w3.org/1998/Math/MathML">
            <apply>
              <times/>
              <cn> 0.003 </cn>
              <ci> W1pox </ci>
              <apply>
                <power/>
                <ci> XSumNegF </ci>
                <cn> 2 </cn>
              </apply>
            </apply>
          </math>
        </kineticLaw>
      </reaction>
      <reaction id="R25" reversible="false" fast="false">
        <listOfReactants>
          <speciesReference species="W2pox"/>
        </listOfReactants>
        <listOfProducts>
          <speciesReference species="W2po"/>
        </listOfProducts>
        <kineticLaw>
          <notes>
            <body xmlns="http://www.w3.org/1999/xhtml">
              <p>Flux name: F25</p>
            </body>
          </notes>
          <math xmlns="http://www.w3.org/1998/Math/MathML">
            <apply>
              <times/>
              <cn> 0.003 </cn>
              <ci> W2pox </ci>
              <apply>
                <power/>
                <ci> XSumNegF </ci>
                <cn> 2 </cn>
              </apply>
            </apply>
          </math>
        </kineticLaw>
      </reaction>
      <reaction id="R22" reversible="false" fast="false">
        <listOfReactants>
          <speciesReference species="W0nex"/>
        </listOfReactants>
        <listOfProducts>
          <speciesReference species="W0ne"/>
        </listOfProducts>
        <kineticLaw>
          <notes>
            <body xmlns="http://www.w3.org/1999/xhtml">
              <p>Flux name: F22</p>
            </body>
          </notes>
          <math xmlns="http://www.w3.org/1998/Math/MathML">
            <apply>
              <times/>
              <cn> 0.003 </cn>
              <ci> W0nex </ci>
              <apply>
                <power/>
                <ci> XSumNegF </ci>
                <cn> 2 </cn>
              </apply>
            </apply>
          </math>
        </kineticLaw>
      </reaction>
      <reaction id="R6" reversible="false" fast="false">
        <listOfReactants>
          <speciesReference species="W1ne"/>
        </listOfReactants>
        <listOfProducts>
          <speciesReference species="W1nex"/>
        </listOfProducts>
        <listOfModifiers>
          <modifierSpeciesReference species="X1v0"/>
        </listOfModifiers>
        <kineticLaw>
          <notes>
            <body xmlns="http://www.w3.org/1999/xhtml">
              <p>Flux name: F6</p>
            </body>
          </notes>
          <math xmlns="http://www.w3.org/1998/Math/MathML">
            <apply>
              <times/>
              <cn> 0.1 </cn>
              <apply>
                <power/>
                <ci> X1v0 </ci>
                <cn> 2 </cn>
              </apply>
              <ci> W1ne </ci>
            </apply>
          </math>
        </kineticLaw>
      </reaction>
      <reaction id="R7" reversible="false" fast="false">
        <listOfReactants>
          <speciesReference species="W1ne"/>
        </listOfReactants>
        <listOfProducts>
          <speciesReference species="Zne"/>
          <speciesReference species="W1nex"/>
        </listOfProducts>
        <listOfModifiers>
          <modifierSpeciesReference species="X1v1"/>
        </listOfModifiers>
        <kineticLaw>
          <notes>
            <body xmlns="http://www.w3.org/1999/xhtml">
              <p>Flux name: F7</p>
            </body>
          </notes>
          <math xmlns="http://www.w3.org/1998/Math/MathML">
            <apply>
              <times/>
              <cn> 0.1 </cn>
              <apply>
                <power/>
                <ci> X1v1 </ci>
                <cn> 2 </cn>
              </apply>
              <ci> W1ne </ci>
            </apply>
          </math>
        </kineticLaw>
      </reaction>
      <reaction id="R11" reversible="false" fast="false">
        <listOfReactants>
          <speciesReference species="W2ne"/>
        </listOfReactants>
        <listOfProducts>
          <speciesReference species="W2nex"/>
        </listOfProducts>
        <listOfModifiers>
          <modifierSpeciesReference species="X2v0"/>
        </listOfModifiers>
        <kineticLaw>
          <notes>
            <body xmlns="http://www.w3.org/1999/xhtml">
              <p>Flux name: F11</p>
            </body>
          </notes>
          <math xmlns="http://www.w3.org/1998/Math/MathML">
            <apply>
              <times/>
              <cn> 0.1 </cn>
              <apply>
                <power/>
                <ci> X2v0 </ci>
                <cn> 2 </cn>
              </apply>
              <ci> W2ne </ci>
            </apply>
          </math>
        </kineticLaw>
      </reaction>
      <reaction id="R12" reversible="false" fast="false">
        <listOfReactants>
          <speciesReference species="W2ne"/>
        </listOfReactants>
        <listOfProducts>
          <speciesReference species="W2nex"/>
          <speciesReference species="Zne"/>
        </listOfProducts>
        <listOfModifiers>
          <modifierSpeciesReference species="X2v1"/>
        </listOfModifiers>
        <kineticLaw>
          <notes>
            <body xmlns="http://www.w3.org/1999/xhtml">
              <p>Flux name: F12</p>
            </body>
          </notes>
          <math xmlns="http://www.w3.org/1998/Math/MathML">
            <apply>
              <times/>
              <cn> 0.1 </cn>
              <apply>
                <power/>
                <ci> X2v1 </ci>
                <cn> 2 </cn>
              </apply>
              <ci> W2ne </ci>
            </apply>
          </math>
        </kineticLaw>
      </reaction>
      <reaction id="R1" reversible="false" fast="false">
        <listOfReactants>
          <speciesReference species="W0po"/>
        </listOfReactants>
        <listOfProducts>
          <speciesReference species="W0pox"/>
          <speciesReference species="Zpo"/>
        </listOfProducts>
        <kineticLaw>
          <notes>
            <body xmlns="http://www.w3.org/1999/xhtml">
              <p>Flux name: F1</p>
            </body>
          </notes>
          <math xmlns="http://www.w3.org/1998/Math/MathML">
            <apply>
              <times/>
              <cn> 0.025 </cn>
              <ci> W0po </ci>
              <apply>
                <power/>
                <ci> XSum </ci>
                <cn> 2 </cn>
              </apply>
            </apply>
          </math>
        </kineticLaw>
      </reaction>
      <reaction id="R24" reversible="false" fast="false">
        <listOfReactants>
          <speciesReference species="W1nex"/>
        </listOfReactants>
        <listOfProducts>
          <speciesReference species="W1ne"/>
        </listOfProducts>
        <kineticLaw>
          <notes>
            <body xmlns="http://www.w3.org/1999/xhtml">
              <p>Flux name: F24</p>
            </body>
          </notes>
          <math xmlns="http://www.w3.org/1998/Math/MathML">
            <apply>
              <times/>
              <cn> 0.003 </cn>
              <ci> W1nex </ci>
              <apply>
                <power/>
                <ci> XSumNegF </ci>
                <cn> 2 </cn>
              </apply>
            </apply>
          </math>
        </kineticLaw>
      </reaction>
      <reaction id="R26" reversible="false" fast="false">
        <listOfReactants>
          <speciesReference species="W2nex"/>
        </listOfReactants>
        <listOfProducts>
          <speciesReference species="W2ne"/>
        </listOfProducts>
        <kineticLaw>
          <notes>
            <body xmlns="http://www.w3.org/1999/xhtml">
              <p>Flux name: F26</p>
            </body>
          </notes>
          <math xmlns="http://www.w3.org/1998/Math/MathML">
            <apply>
              <times/>
              <cn> 0.003 </cn>
              <ci> W2nex </ci>
              <apply>
                <power/>
                <ci> XSumNegF </ci>
                <cn> 2 </cn>
              </apply>
            </apply>
          </math>
        </kineticLaw>
      </reaction>
      <reaction id="R21" reversible="false" fast="false">
        <listOfReactants>
          <speciesReference species="W0pox"/>
        </listOfReactants>
        <listOfProducts>
          <speciesReference species="W0po"/>
        </listOfProducts>
        <kineticLaw>
          <notes>
            <body xmlns="http://www.w3.org/1999/xhtml">
              <p>Flux name: F21</p>
            </body>
          </notes>
          <math xmlns="http://www.w3.org/1998/Math/MathML">
            <apply>
              <times/>
              <cn> 0.003 </cn>
              <ci> W0pox </ci>
              <apply>
                <power/>
                <ci> XSumNegF </ci>
                <cn> 2 </cn>
              </apply>
            </apply>
          </math>
        </kineticLaw>
      </reaction>
      <reaction id="R33" reversible="false" fast="false">
        <listOfReactants>
          <speciesReference species="Dv0"/>
        </listOfReactants>
        <listOfProducts>
          <speciesReference species="W1ne"/>
        </listOfProducts>
        <listOfModifiers>
          <modifierSpeciesReference species="X1v1"/>
          <modifierSpeciesReference species="Yv1"/>
        </listOfModifiers>
        <kineticLaw>
          <notes>
            <body xmlns="http://www.w3.org/1999/xhtml">
              <p>Flux name: F33</p>
            </body>
          </notes>
          <math xmlns="http://www.w3.org/1998/Math/MathML">
            <apply>
              <times/>
              <cn> 0.006 </cn>
              <ci> Dv0 </ci>
              <ci> Yv1 </ci>
              <ci> X1v1 </ci>
            </apply>
          </math>
        </kineticLaw>
      </reaction>
      <reaction id="R36" reversible="false" fast="false">
        <listOfReactants>
          <speciesReference species="Dv1"/>
        </listOfReactants>
        <listOfProducts>
          <speciesReference species="W1po"/>
        </listOfProducts>
        <listOfModifiers>
          <modifierSpeciesReference species="X1v1"/>
          <modifierSpeciesReference species="Yv0"/>
        </listOfModifiers>
        <kineticLaw>
          <notes>
            <body xmlns="http://www.w3.org/1999/xhtml">
              <p>Flux name: F36</p>
            </body>
          </notes>
          <math xmlns="http://www.w3.org/1998/Math/MathML">
            <apply>
              <times/>
              <cn> 0.006 </cn>
              <ci> Dv1 </ci>
              <ci> Yv0 </ci>
              <ci> X1v1 </ci>
            </apply>
          </math>
        </kineticLaw>
      </reaction>
      <reaction id="R35" reversible="false" fast="false">
        <listOfReactants>
          <speciesReference species="Dv1"/>
        </listOfReactants>
        <listOfProducts>
          <speciesReference species="W0po"/>
        </listOfProducts>
        <listOfModifiers>
          <modifierSpeciesReference species="Yv0"/>
        </listOfModifiers>
        <kineticLaw>
          <notes>
            <body xmlns="http://www.w3.org/1999/xhtml">
              <p>Flux name: F35</p>
            </body>
          </notes>
          <math xmlns="http://www.w3.org/1998/Math/MathML">
            <apply>
              <times/>
              <cn> 0.003 </cn>
              <ci> Dv1 </ci>
              <ci> Yv0 </ci>
              <ci> XSum </ci>
            </apply>
          </math>
        </kineticLaw>
      </reaction>
      <reaction id="R32" reversible="false" fast="false">
        <listOfReactants>
          <speciesReference species="Dv0"/>
        </listOfReactants>
        <listOfProducts>
          <speciesReference species="W0ne"/>
        </listOfProducts>
        <listOfModifiers>
          <modifierSpeciesReference species="Yv1"/>
        </listOfModifiers>
        <kineticLaw>
          <notes>
            <body xmlns="http://www.w3.org/1999/xhtml">
              <p>Flux name: F32</p>
            </body>
          </notes>
          <math xmlns="http://www.w3.org/1998/Math/MathML">
            <apply>
              <times/>
              <cn> 0.003 </cn>
              <ci> Dv0 </ci>
              <ci> Yv1 </ci>
              <ci> XSum </ci>
            </apply>
          </math>
        </kineticLaw>
      </reaction>
      <reaction id="R3" reversible="false" fast="false">
        <listOfReactants>
          <speciesReference species="W0po"/>
          <speciesReference species="W0ne"/>
        </listOfReactants>
        <kineticLaw>
          <notes>
            <body xmlns="http://www.w3.org/1999/xhtml">
              <p>Flux name: F3</p>
            </body>
          </notes>
          <math xmlns="http://www.w3.org/1998/Math/MathML">
            <piecewise>
              <piece>
                <apply>
                  <times/>
                  <cn> 0.1 </cn>
                  <ci> W0po </ci>
                </apply>
                <apply>
                  <lt/>
                  <ci> W0po </ci>
                  <ci> W0ne </ci>
                </apply>
              </piece>
              <otherwise>
                <apply>
                  <times/>
                  <cn> 0.1 </cn>
                  <ci> W0ne </ci>
                </apply>
              </otherwise>
            </piecewise>
          </math>
        </kineticLaw>
      </reaction>
      <reaction id="R8" reversible="false" fast="false">
        <listOfReactants>
          <speciesReference species="W1ne"/>
          <speciesReference species="W1po"/>
        </listOfReactants>
        <kineticLaw>
          <notes>
            <body xmlns="http://www.w3.org/1999/xhtml">
              <p>Flux name: F8</p>
            </body>
          </notes>
          <math xmlns="http://www.w3.org/1998/Math/MathML">
            <piecewise>
              <piece>
                <apply>
                  <times/>
                  <cn> 0.1 </cn>
                  <ci> W1po </ci>
                </apply>
                <apply>
                  <lt/>
                  <ci> W1po </ci>
                  <ci> W1ne </ci>
                </apply>
              </piece>
              <otherwise>
                <apply>
                  <times/>
                  <cn> 0.1 </cn>
                  <ci> W1ne </ci>
                </apply>
              </otherwise>
            </piecewise>
          </math>
        </kineticLaw>
      </reaction>
      <reaction id="R13" reversible="false" fast="false">
        <listOfReactants>
          <speciesReference species="W2po"/>
          <speciesReference species="W2ne"/>
        </listOfReactants>
        <kineticLaw>
          <notes>
            <body xmlns="http://www.w3.org/1999/xhtml">
              <p>Flux name: F13</p>
            </body>
          </notes>
          <math xmlns="http://www.w3.org/1998/Math/MathML">
            <piecewise>
              <piece>
                <apply>
                  <times/>
                  <cn> 0.1 </cn>
                  <ci> W2po </ci>
                </apply>
                <apply>
                  <lt/>
                  <ci> W2po </ci>
                  <ci> W2ne </ci>
                </apply>
              </piece>
              <otherwise>
                <apply>
                  <times/>
                  <cn> 0.1 </cn>
                  <ci> W2ne </ci>
                </apply>
              </otherwise>
            </piecewise>
          </math>
        </kineticLaw>
      </reaction>
      <reaction id="R28" reversible="false" fast="false">
        <listOfReactants>
          <speciesReference species="Yv0"/>
        </listOfReactants>
        <kineticLaw>
          <notes>
            <body xmlns="http://www.w3.org/1999/xhtml">
              <p>Flux name: F28</p>
            </body>
          </notes>
          <math xmlns="http://www.w3.org/1998/Math/MathML">
            <apply>
              <times/>
              <cn> 0.001 </cn>
              <ci> Yv0 </ci>
              <ci> XSumNegF </ci>
            </apply>
          </math>
        </kineticLaw>
      </reaction>
      <reaction id="R29" reversible="false" fast="false">
        <listOfReactants>
          <speciesReference species="Yv1"/>
        </listOfReactants>
        <kineticLaw>
          <notes>
            <body xmlns="http://www.w3.org/1999/xhtml">
              <p>Flux name: F29</p>
            </body>
          </notes>
          <math xmlns="http://www.w3.org/1998/Math/MathML">
            <apply>
              <times/>
              <cn> 0.001 </cn>
              <ci> Yv1 </ci>
              <ci> XSumNegF </ci>
            </apply>
          </math>
        </kineticLaw>
      </reaction>
      <reaction id="R27" reversible="false" fast="false">
        <listOfReactants>
          <speciesReference species="Yv0"/>
          <speciesReference species="Yv1"/>
        </listOfReactants>
        <kineticLaw>
          <notes>
            <body xmlns="http://www.w3.org/1999/xhtml">
              <p>Flux name: F27</p>
            </body>
          </notes>
          <math xmlns="http://www.w3.org/1998/Math/MathML">
            <piecewise>
              <piece>
                <apply>
                  <times/>
                  <cn> 0.5 </cn>
                  <ci> Yv0 </ci>
                </apply>
                <apply>
                  <lt/>
                  <ci> Yv0 </ci>
                  <ci> Yv1 </ci>
                </apply>
              </piece>
              <otherwise>
                <apply>
                  <times/>
                  <cn> 0.5 </cn>
                  <ci> Yv1 </ci>
                </apply>
              </otherwise>
            </piecewise>
          </math>
        </kineticLaw>
      </reaction>
    </listOfReactions>
  </model>
</sbml>
