<?xml version="1.0" encoding="UTF-8"?>
<sbml xmlns="http://www.sbml.org/sbml/level2/version4" level="2" version="4">
  <model id="MPModel">
    <notes>
      <body xmlns="http://www.w3.org/1999/xhtml">
        <p>
          <h2>
            <center>Sirio</center>
          </h2>
        </p>
        <p>Description: Sirio model after Log gain calculation.</p>
        <p>This model has been automatically generated by the MetaPlab SBML plugin.<br/>
The original model has <b>time unit = 1.0 seconds</b> and <b>time resolution = 1.0</b>
        <br/>
In order to obtain the same dynamics of the original model, the user should calculate it by means of the <b>Euler algorithm with dT = 1.0</b> (which corresponds to 1.0 seconds)</p>
      </body>
    </notes>
    <listOfCompartments>
      <compartment id="skin" name="skin membrane" size="1" units="volume"/>
    </listOfCompartments>
    <listOfSpecies>
      <species id="A" name="A" compartment="skin" initialConcentration="100" substanceUnits="substance" boundaryCondition="true" constant="true"/>
      <species id="B" name="B" compartment="skin" initialConcentration="100" substanceUnits="substance" boundaryCondition="true" constant="true"/>
      <species id="C" name="C" compartment="skin" initialConcentration="1" substanceUnits="substance" boundaryCondition="true" constant="true"/>
    </listOfSpecies>
    <listOfReactions>
      <reaction id="R2" reversible="false" fast="false">
        <listOfReactants>
          <speciesReference species="A"/>
        </listOfReactants>
        <listOfProducts>
          <speciesReference species="B"/>
        </listOfProducts>
        <kineticLaw>
          <notes>
            <body xmlns="http://www.w3.org/1999/xhtml">
              <p>Flux name: F2</p>
            </body>
          </notes>
          <math xmlns="http://www.w3.org/1998/Math/MathML">
            <cn> 0 </cn>
          </math>
        </kineticLaw>
      </reaction>
      <reaction id="R4" reversible="false" fast="false">
        <listOfReactants>
          <speciesReference species="A"/>
        </listOfReactants>
        <listOfProducts>
          <speciesReference species="C"/>
        </listOfProducts>
        <kineticLaw>
          <notes>
            <body xmlns="http://www.w3.org/1999/xhtml">
              <p>Flux name: F4</p>
            </body>
          </notes>
          <math xmlns="http://www.w3.org/1998/Math/MathML">
            <cn> 0 </cn>
          </math>
        </kineticLaw>
      </reaction>
      <reaction id="R1" reversible="false" fast="false">
        <listOfReactants>
          <speciesReference species="A"/>
        </listOfReactants>
        <listOfProducts>
          <speciesReference species="A" stoichiometry="2"/>
        </listOfProducts>
        <kineticLaw>
          <notes>
            <body xmlns="http://www.w3.org/1999/xhtml">
              <p>Flux name: F1</p>
            </body>
          </notes>
          <math xmlns="http://www.w3.org/1998/Math/MathML">
            <cn> 0 </cn>
          </math>
        </kineticLaw>
      </reaction>
      <reaction id="R3" reversible="false" fast="false">
        <listOfReactants>
          <speciesReference species="B"/>
        </listOfReactants>
        <kineticLaw>
          <notes>
            <body xmlns="http://www.w3.org/1999/xhtml">
              <p>Flux name: F3</p>
            </body>
          </notes>
          <math xmlns="http://www.w3.org/1998/Math/MathML">
            <cn> 0 </cn>
          </math>
        </kineticLaw>
      </reaction>
      <reaction id="R5" reversible="false" fast="false">
        <listOfReactants>
          <speciesReference species="C"/>
        </listOfReactants>
        <kineticLaw>
          <notes>
            <body xmlns="http://www.w3.org/1999/xhtml">
              <p>Flux name: F5</p>
            </body>
          </notes>
          <math xmlns="http://www.w3.org/1998/Math/MathML">
            <cn> 0 </cn>
          </math>
        </kineticLaw>
      </reaction>
    </listOfReactions>
  </model>
</sbml>
